claude-daemon/__init__.py
claude-daemon/analyzer.py
claude-daemon/app.py
claude-daemon/cli_integration.py
claude-daemon/client.py
claude-daemon/fraud_detector.py
claude-daemon/response_flow.py
claude-daemon/test_cases.py
trello_cli/__init__.py
trello_cli/cli.py
trello_cli/client.py
trello_cli/config.py
trello_cli/context_analyzer.py
trello_cli/plugins.py
trello_cli/validators.py
trello_cli/commands/__init__.py
trello_cli/commands/audit.py
trello_cli/commands/board.py
trello_cli/commands/bulk.py
trello_cli/commands/card.py
trello_cli/commands/checklist.py
trello_cli/commands/discovery.py
trello_cli/commands/export.py
trello_cli/commands/help.py
trello_cli/commands/label.py
trello_cli/commands/list.py
trello_cli/commands/members.py
trello_cli/commands/migrate.py
trello_cli/commands/query.py
trello_cli/commands/quick.py
trello_cli/commands/reporting.py
trello_cli/commands/sprint.py
trello_cli/commands/standardize.py
trello_cli/commands/validation.py
trello_cli/utils/__init__.py
trello_cli/utils/formatters.py
trello_cli/utils/validators.py
trello_cli_python-2.2.2.data/scripts/trello
trello_cli_python-2.2.2.dist-info/licenses/LICENSE
trello_cli_python-2.2.2.dist-info/METADATA
trello_cli_python-2.2.2.dist-info/WHEEL
trello_cli_python-2.2.2.dist-info/entry_points.txt
trello_cli_python-2.2.2.dist-info/top_level.txt
trello_cli_python-2.2.2.dist-info/RECORD
