Metadata-Version: 2.4
Name: trello-cli-python
Version: 2.2.2
Summary: Official Python CLI for Trello - Optimized for agile workflows
Home-page: https://github.com/bernardurizaorozco/trello-cli-python
Author: Bernard Uriza Orozco
Author-email: bernard@example.com
Classifier: Development Status :: 4 - Beta
Classifier: Intended Audience :: Developers
Classifier: Topic :: Software Development :: Build Tools
Classifier: License :: OSI Approved :: MIT License
Classifier: Programming Language :: Python :: 3
Classifier: Programming Language :: Python :: 3.7
Classifier: Programming Language :: Python :: 3.8
Classifier: Programming Language :: Python :: 3.9
Classifier: Programming Language :: Python :: 3.10
Classifier: Programming Language :: Python :: 3.11
Requires-Python: >=3.7
License-File: LICENSE
Requires-Dist: py-trello>=0.19.0
Requires-Dist: python-dateutil>=2.8.0
Requires-Dist: python-dotenv>=0.19.0
Requires-Dist: anthropic>=0.7.0
Dynamic: author
Dynamic: author-email
Dynamic: classifier
Dynamic: description
Dynamic: description-content-type
Dynamic: home-page
Dynamic: license-file
Dynamic: requires-dist
Dynamic: requires-python
Dynamic: summary
